duplremover/__init__.py
duplremover/duplicate_remover.py
duplremover/multi_workers.py
duplremover/resourse_and_gears.py
duplremover/set_logger.py
dupremover-0.1.3.dist-info/LICENSE
dupremover-0.1.3.dist-info/METADATA
dupremover-0.1.3.dist-info/WHEEL
dupremover-0.1.3.dist-info/entry_points.txt
dupremover-0.1.3.dist-info/top_level.txt
dupremover-0.1.3.dist-info/RECORD
