Metadata-Version: 2.1
Name: dupremover
Version: 0.1.3
Summary: a tool to remove any duplicated files
Home-page: https://github.com/GuardianGH/duplremover/tree/master/duplremover
Author: Guardian
Author-email: zhling2012@live.com
Maintainer: Guardian
Maintainer-email: zhling2012@live.com
License: UNKNOWN
Platform: UNKNOWN
Classifier: Programming Language :: Python :: 3
Classifier: License :: OSI Approved :: MIT License
Classifier: Operating System :: OS Independent
License-File: LICENSE
Requires-Dist: tqdm (~=4.64.0)
